Workbook
Name rendimento_carteira: Planilha1!$E$17

Sheet Planilha1
C15: CONFIGURAÇÕES
C16: Salários | E16: 5000
C17: Rendimento Carteira | E17: 0.01
C18: Sugestão de Investimento (30%) | E18: =E16*30% -> 1500
C21: Investimentos Mensal
C22: Quanto investir por mês? | E22: 1000
C23: Por quanto anos? | E23: 5
C24: Taxa de rendimento mensal? | E24: 0.01079
C25: Patrimônio Acumulado | E25: =FV(E24,E23*12,E22*-1) -> 83776.914
C26: Dividendos Mensais | E26: =E25*$E$17 -> 837.76914
C29: Cenários | E29: Dividendo
A30: 2 | C30: Quanto em 2 anos? | D30: =FV($E$24,$A30*12,$E$22*-1) -> 27227.627 | E30: =D30*$E$17 -> 272.27627
A31: 5 | C31: Quanto em 5 anos? | D31: =FV($E$24,$A31*12,$E$22*-1) -> 83776.914 | E31: =D31*$E$17 -> 837.76914
A32: 10 | C32: Quanto em 10 anos? | D32: =FV($E$24,$A32*12,$E$22*-1) -> 243284.21 | E32: =D32*$E$17 -> 2432.8421
A33: 20 | C33: Quanto em 20 anos? | D33: =FV($E$24,$A33*12,$E$22*-1) -> 1125198.4 | E33: =D33*$E$17 -> 11251.984
A34: 30 | C34: Quanto em 30 anos? | D34: =FV($E$24,$A34*12,$E$22*-1) -> 4322169.7 | E34: =D34*$E$17 -> 43221.697
C37: Perfil | D37: Agressivo
C38: Valor a ser investido por mês | D38: =E22 -> 1000
C40: Tipo de FII | D40: Percentual Sugerido | E40: Valores
C41: PAPEL | D41: =VLOOKUP($D$37&"-"&C41,Planilha2!A:D,4,FALSE) -> 0.5 | E41: =$D$38*D41 -> 500
C42: TIJOLO | D42: =VLOOKUP($D$37&"-"&C42,Planilha2!A:D,4,FALSE) -> 0.1 | E42: =$D$38*D42 -> 100
C43: HÍBRIDO | D43: =VLOOKUP($D$37&"-"&C43,Planilha2!A:D,4,FALSE) -> 0.05 | E43: =$D$38*D43 -> 50
C44: FOF's | D44: =VLOOKUP($D$37&"-"&C44,Planilha2!A:D,4,FALSE) -> 0.05 | E44: =$D$38*D44 -> 50
C45: DESENVOLVIMENTO | D45: =VLOOKUP($D$37&"-"&C45,Planilha2!A:D,4,FALSE) -> 0.2 | E45: =$D$38*D45 -> 200
C46: HOTELARIAS | D46: =VLOOKUP($D$37&"-"&C46,Planilha2!A:D,4,FALSE) -> 0.1 | E46: =$D$38*D46 -> 100
E47: =SUM(E41:E46) -> 1000

Sheet Planilha2
A8: Chave | B8: Perfil | C8: Tipo de FII | D8: % | F8: Moderado-TIJOLO | G8: =VLOOKUP(F8,$A:$D,4,FALSE) -> 0.4
A9: =$B$9&"-"&C9 -> Conservador-PAPEL | B9: Conservador | C9: PAPEL | D9: 0.3
A10: =$B$9&"-"&C10 -> Conservador-TIJOLO | B10: Conservador | C10: TIJOLO | D10: 0.5
A11: =$B$9&"-"&C11 -> Conservador-HÍBRIDO | B11: Conservador | C11: HÍBRIDO | D11: 0.1
A12: =$B$9&"-"&C12 -> Conservador-FOF's | B12: Conservador | C12: FOF's | D12: 0.1
A13: =$B$9&"-"&C13 -> Conservador-DESENVOLVIMENTO | B13: Conservador | C13: DESENVOLVIMENTO | D13: 0
A14: =$B$9&"-"&C14 -> Conservador-HOTELARIAS | B14: Conservador | C14: HOTELARIAS | D14: 0
A15: =$B$15&"-"&C15 -> Moderado-PAPEL | B15: Moderado | C15: PAPEL | D15: 0.32
A16: =$B$15&"-"&C16 -> Moderado-TIJOLO | B16: Moderado | C16: TIJOLO | D16: 0.4
A17: =$B$15&"-"&C17 -> Moderado-HÍBRIDO | B17: Moderado | C17: HÍBRIDO | D17: 0.08
A18: =$B$15&"-"&C18 -> Moderado-FOF's | B18: Moderado | C18: FOF's | D18: 0.1
A19: =$B$15&"-"&C19 -> Moderado-DESENVOLVIMENTO | B19: Moderado | C19: DESENVOLVIMENTO | D19: 0.1
A20: =$B$15&"-"&C20 -> Moderado-HOTELARIAS | B20: Moderado | C20: HOTELARIAS | D20: 0.1
A21: =$B$21&"-"&C21 -> Agressivo-PAPEL | B21: Agressivo | C21: PAPEL | D21: 0.5
A22: =$B$21&"-"&C22 -> Agressivo-TIJOLO | B22: Agressivo | C22: TIJOLO | D22: 0.1
A23: =$B$21&"-"&C23 -> Agressivo-HÍBRIDO | B23: Agressivo | C23: HÍBRIDO | D23: 0.05
A24: =$B$21&"-"&C24 -> Agressivo-FOF's | B24: Agressivo | C24: FOF's | D24: 0.05
A25: =$B$21&"-"&C25 -> Agressivo-DESENVOLVIMENTO | B25: Agressivo | C25: DESENVOLVIMENTO | D25: 0.2
A26: =$B$21&"-"&C26 -> Agressivo-HOTELARIAS | B26: Agressivo | C26: HOTELARIAS | D26: 0.1
